pdsystem.py
pdsystem-1.0.4.dist-info/LICENCE.txt
pdsystem-1.0.4.dist-info/METADATA
pdsystem-1.0.4.dist-info/WHEEL
pdsystem-1.0.4.dist-info/top_level.txt
pdsystem-1.0.4.dist-info/RECORD
